paaszk/__init__.py
paaszk/config.py
paaszk/crypto.py
paaszk/dropbox_backend.py
paaszk/file_ops.py
paaszk/googledrive_backend.py
paaszk/main.py
paaszk/s3_backend.py
paaszk-0.1.5.dist-info/licenses/LICENSE
paaszk-0.1.5.dist-info/METADATA
paaszk-0.1.5.dist-info/WHEEL
paaszk-0.1.5.dist-info/entry_points.txt
paaszk-0.1.5.dist-info/top_level.txt
paaszk-0.1.5.dist-info/RECORD
