Metadata-Version: 2.4
Name: paaszk
Version: 0.1.5
Summary: A zero-knowledge encrypted vault CLI tool.
Author-email: Pedro Rodrigues <pedrex1997@gmail.com>
License: MIT
Project-URL: Homepage, https://github.com/pedrorodrigues1997/PaaSZK
Project-URL: Bug Tracker, https://github.com/pedrorodrigues1997/PaaSZK/issues
Requires-Python: >=3.8
License-File: LICENSE
Requires-Dist: cryptography
Requires-Dist: argon2-cffi
Requires-Dist: pyyaml
Requires-Dist: boto3
Requires-Dist: dropbox
Requires-Dist: google-api-python-client
Requires-Dist: google-auth
Requires-Dist: google-auth-oauthlib
Requires-Dist: minio
Dynamic: license-file
